ostir/ViennaRNA.py
ostir/__init__.py
ostir/data_classes.py
ostir/ostir.py
ostir/ostir_calculations.py
ostir/ostir_engine.py
ostir/ostir_factory.py
ostir/ostir_farm.py
ostir/ostir_worker.py
ostir/rna_turner1999.par
ostir/rna_turner2004.par
ostir/shortcuts.py
OSTIR-1.1.3.dist-info/LICENSE
OSTIR-1.1.3.dist-info/METADATA
OSTIR-1.1.3.dist-info/WHEEL
OSTIR-1.1.3.dist-info/entry_points.txt
OSTIR-1.1.3.dist-info/top_level.txt
OSTIR-1.1.3.dist-info/RECORD
