Metadata-Version: 2.1
Name: OSTIR
Version: 1.1.3
Summary: Open Source Transcription Initiation Rates
Home-page: https://github.com/barricklab/ostir
Author: Cameron Roots, Alexandra Lukasiewicz, Jeffrey Barrick, 
Author-email: croots@utexas.edu
Classifier: Programming Language :: Python :: 3
Classifier: License :: OSI Approved :: GNU General Public License v3 or later (GPLv3+)
Classifier: Operating System :: OS Independent
Requires-Python: >=3.8
License-File: LICENSE
Requires-Dist: numpy
Provides-Extra: status
Requires-Dist: progress; extra == "status"
Provides-Extra: nice-text
Requires-Dist: rich; extra == "nice-text"
